rootfs/__init__.py
rootfs/__pycache__/__init__.cpython-311.pyc
rootfs/bin/__init__.py
rootfs/bin/__pycache__/__init__.cpython-311.pyc
rootfs/etc/__init__.py
rootfs/etc/animals
rootfs/etc/colors
rootfs/etc/sports
rootfs/etc/__pycache__/__init__.cpython-311.pyc
rootfs/usr/__init__.py
rootfs/usr/__pycache__/__init__.cpython-311.pyc
rootfs/usr/share/__init__.py
rootfs/usr/share/bluecow.jpg
rootfs/usr/share/cats.jpg
rootfs/usr/share/chick.jpg
rootfs/usr/share/chicken.jpg
rootfs/usr/share/chicken.pdf
rootfs/usr/share/cooked.jpg
rootfs/usr/share/cow.pdf
rootfs/usr/share/racket.jpg
rootfs/usr/share/redcow.jpg
rootfs/usr/share/soccer.jpg
rootfs/usr/share/__pycache__/__init__.cpython-311.pyc
rootfs-0.0.2.dist-info/METADATA
rootfs-0.0.2.dist-info/WHEEL
rootfs-0.0.2.dist-info/entry_points.txt
rootfs-0.0.2.dist-info/top_level.txt
rootfs-0.0.2.dist-info/RECORD
